[
  {
    "id": 0,
    "nombre": "default",
    "apellido": "default",
    "email": "mail@default.com",
    "password": "default"
  },
  {
    "id": "d2f2a583-28d9-4778-aa02-54572ac321ca",
    "nombre": "Emanuel",
    "apellido": "Tejerina",
    "email": "emanueljtejerina@gmail.com",
    "password": "$2a$10$lQuS8SbhoejZCSiYEYa2kuby/EcAUarLX./KwupahqSoaeVHNBZoe"
  },
  {
    "id": "a7b048d5-62be-4503-87ca-a392c5b6b6b6",
    "nombre": "Mars123",
    "apellido": "rojo",
    "email": "123@gmail.com",
    "password": "$2a$10$8R6IwzLWq0MJ103kIomUXux/BmTPqBgneRKmg4dqqY/BMrJUiO92W"
  }
]